genesis/__init__.py
genesis/_main.py
genesis/constants.py
genesis/datatypes.py
genesis/repr_base.py
genesis/styles.py
genesis/version.py
genesis/assets/meshes/axis.obj
genesis/assets/meshes/bunny.obj
genesis/assets/meshes/cloth.obj
genesis/assets/meshes/cross_cutter.obj
genesis/assets/meshes/dragon.obj
genesis/assets/meshes/duck.obj
genesis/assets/meshes/icecream_dispenser.obj
genesis/assets/meshes/sphere.obj
genesis/assets/meshes/stirrer.obj
genesis/assets/meshes/tank.obj
genesis/assets/meshes/terrain_45.obj
genesis/assets/meshes/Airplane/airplane.mtl
genesis/assets/meshes/Airplane/airplane.obj
genesis/assets/meshes/Airplane/textures/diffuse.dds
genesis/assets/meshes/Airplane/textures/normal.png
genesis/assets/meshes/bathtub/bathtub.obj
genesis/assets/meshes/bathtub/material.mtl
genesis/assets/meshes/boat/boat.obj
genesis/assets/meshes/boat/material.mtl
genesis/assets/meshes/boat/material_0.png
genesis/assets/meshes/boat/material_1.png
genesis/assets/meshes/boat/material_10.png
genesis/assets/meshes/boat/material_11.png
genesis/assets/meshes/boat/material_12.png
genesis/assets/meshes/boat/material_13.png
genesis/assets/meshes/boat/material_14.png
genesis/assets/meshes/boat/material_15.png
genesis/assets/meshes/boat/material_2.png
genesis/assets/meshes/boat/material_3.png
genesis/assets/meshes/boat/material_4.png
genesis/assets/meshes/boat/material_5.png
genesis/assets/meshes/boat/material_6.png
genesis/assets/meshes/boat/material_7.png
genesis/assets/meshes/boat/material_8.png
genesis/assets/meshes/boat/material_9.png
genesis/assets/meshes/camera/camera.obj
genesis/assets/meshes/camera/material.mtl
genesis/assets/meshes/camera/material_0.png
genesis/assets/meshes/chopping-board/source/chopping_board.glb
genesis/assets/meshes/chopping-board/textures/chopping_board_tx_0.png
genesis/assets/meshes/dragon/dragon.obj
genesis/assets/meshes/dragon/material.mtl
genesis/assets/meshes/dragon/material_0.png
genesis/assets/meshes/duck/duck.obj
genesis_world-0.3.11.dist-info/licenses/LICENSE
genesis_world-0.3.11.dist-info/METADATA
genesis_world-0.3.11.dist-info/WHEEL
genesis_world-0.3.11.dist-info/entry_points.txt
genesis_world-0.3.11.dist-info/top_level.txt
genesis_world-0.3.11.dist-info/RECORD
