Metadata-Version: 2.4
Name: genesis-world
Version: 0.3.11
Summary: A universal and generative physics engine
Requires-Python: <3.14,>=3.10
License-File: LICENSE
Requires-Dist: psutil
Requires-Dist: gstaichi==4.6.0
Requires-Dist: pydantic>=2.11.0
Requires-Dist: numpy>=1.26.4
Requires-Dist: trimesh
Requires-Dist: scipy>=1.14
Requires-Dist: libigl
Requires-Dist: py-cpuinfo
Requires-Dist: mujoco>=3.2.5
Requires-Dist: moviepy>=2.0.0
Requires-Dist: pyglet!=2.1.8,>=1.5
Requires-Dist: freetype-py
Requires-Dist: PyOpenGL>=3.1.4
Requires-Dist: numba
Requires-Dist: pymeshlab
Requires-Dist: pycollada
Requires-Dist: pygltflib==1.16.0
Requires-Dist: tetgen<0.7.0,>=0.6.4; platform_machine != "aarch64"
Requires-Dist: PyGEL3D
Requires-Dist: vtk
Requires-Dist: Pillow>11.0
Requires-Dist: opencv-python
Requires-Dist: scikit-image
Requires-Dist: coacd
Requires-Dist: rtree
Requires-Dist: z3-solver
Requires-Dist: OpenEXR
Requires-Dist: gs-madrona==0.0.5; platform_system == "Linux" and (platform_machine == "x86_64" or platform_machine == "AMD64")
Requires-Dist: fast_simplification>=0.1.12
Requires-Dist: pysplashsurf==0.14.*
Provides-Extra: dev
Requires-Dist: black; extra == "dev"
Requires-Dist: pytest; extra == "dev"
Requires-Dist: pytest-xdist; extra == "dev"
Requires-Dist: pytest-forked; extra == "dev"
Requires-Dist: pytest-random-order; extra == "dev"
Requires-Dist: pytest-print; extra == "dev"
Requires-Dist: pytest-rerunfailures!=16.0; extra == "dev"
Requires-Dist: syrupy; extra == "dev"
Requires-Dist: huggingface_hub[hf_xet]; extra == "dev"
Requires-Dist: wandb; extra == "dev"
Requires-Dist: ipython; extra == "dev"
Requires-Dist: mujoco<3.4.0,>=3.3.6; extra == "dev"
Requires-Dist: matplotlib>=3.7.0; extra == "dev"
Requires-Dist: av; extra == "dev"
Provides-Extra: docs
Requires-Dist: sphinx==6.2.1; extra == "docs"
Requires-Dist: sphinx-autobuild; extra == "docs"
Requires-Dist: pydata_sphinx_theme; extra == "docs"
Requires-Dist: sphinxcontrib.spelling; extra == "docs"
Requires-Dist: sphinx-autodoc-typehints; extra == "docs"
Requires-Dist: sphinx_copybutton; extra == "docs"
Requires-Dist: myst-parser; extra == "docs"
Requires-Dist: sphinx-subfigure; extra == "docs"
Requires-Dist: sphinxcontrib-video; extra == "docs"
Requires-Dist: sphinx-togglebutton; extra == "docs"
Requires-Dist: sphinx_design; extra == "docs"
Provides-Extra: render
Requires-Dist: pybind11[global]; extra == "render"
Requires-Dist: open3d; extra == "render"
Provides-Extra: usd
Requires-Dist: usd-core<25.11; extra == "usd"
Dynamic: license-file
